{
	"animations": [
		{
			"loop": false,
			"offsets": [
				0,
				0
			],
			"anim": "idle",
			"fps": 12,
			"name": "BF idle dance",
			"indices": []
		},
		{
			"loop": false,
			"offsets": [
				-10,
				-9
			],
			"anim": "singDOWN",
			"fps": 12,
			"name": "BF NOTE DOWN0",
			"indices": []
		},
		{
			"loop": false,
			"offsets": [
				18,
				-9
			],
			"anim": "singUP",
			"fps": 12,
			"name": "BF NOTE UP0",
			"indices": []
		},
		{
			"offsets": [
				18,
				-9
			],
			"indices": [],
			"fps": 12,
			"anim": "singLEFT",
			"loop": false,
			"name": "BF NOTE RIGHT0"
		},
		{
			"offsets": [
				18,
				-9
			],
			"indices": [],
			"fps": 12,
			"anim": "singRIGHT",
			"loop": false,
			"name": "BF NOTE LEFT0"
		}
	],
	"no_antialiasing": true,
	"image": "characters/BF-Melting",
	"position": [
		-30,
		460
	],
	"healthicon": "pixelMeltBF",
	"flip_x": true,
	"healthbar_colors": [
		49,
		189,
		255
	],
	"camera_position": [
		60,
		-200
	],
	"sing_duration": 4,
	"scale": 8.99999999999999
}